effortless_config/VERSION
effortless_config/__init__.py
effortless_config/__init__.pyi
effortless_config/base62.py
effortless_config/config.py
effortless_config/py.typed
effortless_config-0.7.0.dist-info/METADATA
effortless_config-0.7.0.dist-info/WHEEL
effortless_config-0.7.0.dist-info/top_level.txt
effortless_config-0.7.0.dist-info/RECORD
