Metadata-Version: 2.1
Name: effortless-config
Version: 0.7.0
Summary: Globally scoped configuration with argparse integration
Home-page: https://github.com/andreasjansson/effortless-config
License: UNKNOWN
Platform: UNKNOWN
Classifier: Programming Language :: Python
Requires-Python: >=3.6
